clkUnit/clkUnit.vhd
library IEEE;
use IEEE.std_logic_1164.all;

entity clkUnit is
  generic (facteur_TX : natural := 16);		--frequence_enableRX = frequence_enableTX*facteur, facteur = 16 par defaut
 port (		
   clk, reset : in  std_logic;			--clock du CPU, reset du circuit 
   enableTX   : out std_logic;			--clock de transmission de basse frequence
   enableRX   : out std_logic);			--clock de reception de haute frequence
    
end clkUnit;

architecture behavorial of clkUnit is

begin

enableRX <= clk when (reset = '1') else '0';

process(clk,reset)				--process synchrone

  variable cpt_clk_TX : natural := 1;		--compteur pour regler la frequence de enableTX	
  
  begin
    
    
    
    if(reset = '0') then				--reset du circuit
			
      cpt_clk_TX := 1;				
      enableTX <= '0';

    else 
    
    								--par hypothese enableRX est de meme frequence que le clock du CPU
    	
    	if (rising_edge(clk)) then		 
       
        	if (cpt_clk_TX < facteur_TX) then		--compteur de cycles du clock 
		     enableTX <= '0';
          	     cpt_clk_TX := cpt_clk_TX + 1;
      
        	else 
	
        	    enableTX <= '1';				--enableTX passe a 1 apres 16 (facteur) cycles de clk
                     cpt_clk_TX := 1;
        
                end if;
               
                                 
       end if;
      
   end if;
    
  
  end process;

end behavorial;

UART/RxUnit.vhd
library IEEE;
use IEEE.std_logic_1164.all;

entity RxUnit is
  port (
    clk, reset       : in  std_logic;
    enable           : in  std_logic;
    read             : in  std_logic;
    rxd              : in  std_logic;
    data             : out std_logic_vector(7 downto 0);
    FErr, OErr, DRdy : out std_logic);
end RxUnit;

architecture RxUnit_arch of RxUnit is

  signal tmpClk, tmpRxd : std_logic := '0';

  signal registerR : std_logic_vector (7 downto 0) := "00000000";

  type t_etatC is(repos, attente_start, envoie_bit,attente_bit);	--états de l'automate
  signal etatC : t_etatC;

  type t_etatR is(repos, reception_donnee, reception_parite, reception_fin, fin_transmission, fin_transmission_err);	--états de l'automate
  signal etatR : t_etatR;

begin 

  process(enable,reset)				--process synchrone
    variable cpt_controle : natural := 0;
    variable cpt_envoi : natural := 1;
    variable cpt_tmpClk : natural := 1;		--compteur pour regler l'horloge tmpClk	

    begin

    if(reset = '0') then				--reset du circuit	
      cpt_tmpClk := 1;	
      cpt_envoi := 1;			
      tmpClk <= '0';
      tmpRxd <= '1';
      etatC <= repos;

    elsif (enable = '1') then
      case etatC is 							--automate à états 

      when repos => 
        if (rxd = '0') then
          etatC <= attente_start;
        end if;

      when attente_start => 
        if (cpt_tmpClk < 8) then		--compteur de cycles du clock 
          tmpClk <= '0';
          cpt_tmpClk := cpt_tmpClk + 1;
        else 
          cpt_tmpClk := 1;
        	tmpClk <= '1';				--enableTX passe a 1 apres 16 (facteur) cycles de clk
          tmpRxd <= '0';
          etatC <= envoie_bit;         
        end if;
                                  
      when envoie_bit =>
        tmpClk <= '0';
        if (cpt_envoi <= 10) then
          cpt_envoi := cpt_envoi + 1;
          etatC <= attente_bit;
        else
          if (rxd = '1') then
            cpt_envoi := 1;
            etatC <= repos;
          end if;
        end if;

      when attente_bit => 
        if (cpt_tmpClk < 15) then		--compteur de cycles du clock 
          tmpClk <= '0';
          cpt_tmpClk := cpt_tmpClk + 1;
        else 
          cpt_tmpClk := 1;
          tmpClk <= '1';				--enableTX passe a 1 apres 16 (facteur) cycles de clk
          tmpRxd <= rxd;
          etatC <= envoie_bit;       
        end if;
      end case;
    end if; 
  end process;

  
  process(clk, reset)		  --process synchrone

    variable parite_recu, stop_recu, donnee_recu : std_logic := '0';
    variable parite : std_logic := '0';
    variable cpt_controle : natural := 0;
    
    begin
    
    if(reset = '0') then
      DRdy <= '0';
      FErr <= '0';
      OErr <= '0';
      etatR <= repos;
    elsif(rising_edge(clk)) then
      if(tmpClk = '1') then
          case etatR is
          
          when repos =>
            if (tmpRxd = '0') then
              etatR <= reception_donnee;
            end if;
          
          when reception_donnee =>
            if (cpt_controle = 0) then
              registerR(cpt_controle) <= tmpRxd;
              parite := registerR(cpt_controle);
            elsif (cpt_controle < 7) then
              registerR(cpt_controle) <= tmpRxd;
              parite := parite xor registerR(cpt_controle); 			--calcul du bit de parité
            else
              cpt_controle := 0;
              etatR <= reception_parite;
            end if;
            cpt_controle := cpt_controle + 1;
          
          when reception_parite => 
            parite_recu := tmpRxd;
            etatR <= reception_fin;
          
          when reception_fin =>
            stop_recu := tmpRxd;
            if(not(parite_recu = parite and stop_recu = '1')) then
              FErr <= '1';
              etatR <= fin_transmission_err;
            else
              FErr <= '0';
              DRdy <= '1';
              donnee_recu := '1';
              data <= registerR(0)&registerR(1)&registerR(2)&registerR(3)&registerR(4)&registerR(5)&registerR(6)&registerR(7);
              etatR <= fin_transmission;
            end if;
          when others =>
            null;
          end case;
      else
        case etatR is
          when fin_transmission =>
            DRdy <= '0';
            if (read = '0') then
              OErr <= '1';
              donnee_recu := '0';
            end if;
            etatR <= repos;
          when fin_transmission_err =>
            FErr <= '0';
            etatR <= repos;
          when repos =>
            OErr <= '0';
          
          when others =>
              null;
          end case;
      end if;
    end if;

 end process;


end RxUnit_arch;

testRxUnit.vhd
--------------------------------------------------------------------------------
-- Company: 
-- Engineer:
--
-- Create Date:   12:09:49 10/31/2018
-- Design Name:   
-- Module Name:   testRxUnit.vhd
-- Project Name:  uart
-- Target Device:  
-- Tool versions:  
-- Description:   
-- 
-- VHDL Test Bench Created by ISE for module: RxUnit
-- 
-- Dependencies:
-- 
-- Revision:
-- Revision 0.01 - File Created
-- Additional Comments:
--
-- Notes: 
-- This testbench has been automatically generated using types std_logic and
-- std_logic_vector for the ports of the unit under test.  Xilinx recommends
-- that these types always be used for the top-level I/O of a design in order
-- to guarantee that the testbench will bind correctly to the post-implementation 
-- simulation model.
--------------------------------------------------------------------------------
LIBRARY ieee;
USE ieee.std_logic_1164.ALL;
 
-- Uncomment the following library declaration if using
-- arithmetic functions with Signed or Unsigned values
--USE ieee.numeric_std.ALL;
 
ENTITY testRxUnit IS
END testRxUnit;
 
ARCHITECTURE behavior OF testRxUnit IS 
 
    -- Component Declaration for the Unit Under Test (UUT)
 
    COMPONENT RxUnit
    PORT(
      clk, reset       : in  std_logic;
      enable           : in  std_logic;
      read             : in  std_logic;
      rxd              : in  std_logic;
      data             : out std_logic_vector(7 downto 0);
      FErr, OErr, DRdy : out std_logic);
    END COMPONENT;
   
    COMPONENT clkUnit
    PORT(
         clk : IN  std_logic;
         reset : IN  std_logic;
         enableTX : OUT  std_logic;
         enableRX : OUT  std_logic
        );
    END COMPONENT;	

   signal clk : std_logic := '0';
   signal reset : std_logic := '0';
   signal enableTx : std_logic := '0';
   signal enableRx : std_logic := '0';
   signal read : std_logic := '0';
   signal data : std_logic_vector(7 downto 0) := (others => '0');

   signal rxd : std_logic;
   signal FErr : std_logic;
   signal OErr : std_logic;
   signal DRdy : std_logic;

   -- Clock period definitions
   constant clk_period : time := 10 ns;
   constant enableTX_periode : time := 160 ns;
BEGIN
 
	-- Instantiate the Unit Under Test
   uut0: RxUnit PORT MAP
        (
          clk => clk,
          reset => reset,
          enable => enableRX,
          read => read,
          rxd => rxd,
          data => data,
          FErr => FErr,
          OErr => OErr,
          DRdy => DRdy
        );
   -- Instantiate the clkUnit
   clkUnit1: clkUnit PORT MAP (
          clk => clk,
          reset => reset,
          enableTX => enableTX,
          enableRX => enableRX
        );
		  
   -- Clock process definitions
   clk_process :process
   begin
     clk <= '0';
     wait for clk_period/2;
     clk <= '1';
     wait for clk_period/2;
   end process;
 
 
   -- Stimulus process
   stim_proc: process
   begin		
     rxd <='1';
     -- maintien du reset durant 100 ns.
     wait for 100 ns;	
     reset <= '1';

     wait for 100 ns;	
     rxd <= '0' ;

     wait for enableTX_periode;
     rxd <= '1';
     wait for enableTX_periode;
     rxd <= '0';
     wait for enableTX_periode;
     rxd <= '1';
     wait for enableTX_periode;
     rxd <= '1';
     wait for enableTX_periode;
     rxd <= '0';
     wait for enableTX_periode;
     rxd <= '0';
     wait for enableTX_periode;
     rxd <= '1';
     wait for enableTX_periode;
     rxd <= '0';
     wait for enableTX_periode;
     rxd <= '0';
     wait for enableTX_periode;
     rxd <= '1';

     wait for 9.5*clk_period;
     read <= '1';
     wait for 5*clk_period;
     read <= '0';
     wait;
   end process;

END;

UART/output.vcd
$date
   Tue Jan 18 19:52:38 2022
$end
$version
  P.20131013
$end
$timescale
  1ps
$end
$scope module testrxunit $end
$var wire 1 N clk $end
$var wire 1 O reset $end
$var wire 1 P enabletx $end
$var wire 1 Q enablerx $end
$var wire 1 5 read $end
$var wire 1 > data [7] $end
$var wire 1 = data [6] $end
$var wire 1 < data [5] $end
$var wire 1 ; data [4] $end
$var wire 1 : data [3] $end
$var wire 1 9 data [2] $end
$var wire 1 8 data [1] $end
$var wire 1 7 data [0] $end
$var wire 1 6 rxd $end
$var wire 1 ? ferr $end
$var wire 1 @ oerr $end
$var wire 1 A drdy $end
$scope module uut0 $end
$var wire 1 N clk $end
$var wire 1 O reset $end
$var wire 1 Q enable $end
$var wire 1 5 read $end
$var wire 1 6 rxd $end
$var wire 1 > data [7] $end
$var wire 1 = data [6] $end
$var wire 1 < data [5] $end
$var wire 1 ; data [4] $end
$var wire 1 : data [3] $end
$var wire 1 9 data [2] $end
$var wire 1 8 data [1] $end
$var wire 1 7 data [0] $end
$var wire 1 ? ferr $end
$var wire 1 @ oerr $end
$var wire 1 A drdy $end
$var wire 1 B tmpclk $end
$var wire 1 C tmprxd $end
$var wire 1 K registerr [7] $end
$var wire 1 J registerr [6] $end
$var wire 1 I registerr [5] $end
$var wire 1 H registerr [4] $end
$var wire 1 G registerr [3] $end
$var wire 1 F registerr [2] $end
$var wire 1 E registerr [1] $end
$var wire 1 D registerr [0] $end
$upscope $end
$scope module clkUnit1 $end
$var wire 1 N clk $end
$var wire 1 O reset $end
$var wire 1 P enabletx $end
$var wire 1 Q enablerx $end
$upscope $end
$upscope $end
$enddefinitions $end
#0
$dumpvars
0O
0P
0Q
05
x>
x=
x<
x;
x:
x9
x8
x7
16
0?
0@
0A
0B
1C
0K
0J
0I
0H
0G
0F
0E
0D
0N
$end
#5000
1N
#10000
0N
#15000
1N
#20000
0N
#25000
1N
#30000
0N
#35000
1N
#40000
0N
#45000
1N
#50000
0N
#55000
1N
#60000
0N
#65000
1N
#70000
0N
#75000
1N
#80000
0N
#85000
1N
#90000
0N
#95000
1N
#100000
1O
0N
#105000
1Q
1N
#110000
0Q
0N
#115000
1Q
1N
#120000
0Q
0N
#125000
1Q
1N
#130000
0Q
0N
#135000
1Q
1N
#140000
0Q
0N
#145000
1Q
1N
#150000
0Q
0N
#155000
1Q
1N
#160000
0Q
0N
#165000
1Q
1N
#170000
0Q
0N
#175000
1Q
1N
#180000
0Q
0N
#185000
1Q
1N
#190000
0Q
0N
#195000
1Q
1N
#200000
0Q
06
0N
#205000
1Q
1N
#210000
0Q
0N
#215000
1Q
1N
#220000
0Q
0N
#225000
1Q
1N
#230000
0Q
0N
#235000
1Q
1N
#240000
0Q
0N
#245000
1Q
1N
#250000
0Q
0N
#255000
1P
1Q
1N
#260000
0Q
0N
#265000
0P
1Q
1N
#270000
0Q
0N
#275000
1Q
1N
#280000
0Q
0N
#285000
1Q
1B
0C
1N
#290000
0Q
0N
#295000
1Q
0B
1N
#300000
0Q
0N
#305000
1Q
1N
#310000
0Q
0N
#315000
1Q
1N
#320000
0Q
0N
#325000
1Q
1N
#330000
0Q
0N
#335000
1Q
1N
#340000
0Q
0N
#345000
1Q
1N
#350000
0Q
0N
#355000
1Q
1N
#360000
0Q
16
0N
#365000
1Q
1N
#370000
0Q
0N
#375000
1Q
1N
#380000
0Q
0N
#385000
1Q
1N
#390000
0Q
0N
#395000
1Q
1N
#400000
0Q
0N
#405000
1Q
1N
#410000
0Q
0N
#415000
1P
1Q
1N
#420000
0Q
0N
#425000
0P
1Q
1N
#430000
0Q
0N
#435000
1Q
1N
#440000
0Q
0N
#445000
1Q
1B
1C
1N
#450000
0Q
0N
#455000
1Q
0B
1D
1N
#460000
0Q
0N
#465000
1Q
1N
#470000
0Q
0N
#475000
1Q
1N
#480000
0Q
0N
#485000
1Q
1N
#490000
0Q
0N
#495000
1Q
1N
#500000
0Q
0N
#505000
1Q
1N
#510000
0Q
0N
#515000
1Q
1N
#520000
0Q
06
0N
#525000
1Q
1N
#530000
0Q
0N
#535000
1Q
1N
#540000
0Q
0N
#545000
1Q
1N
#550000
0Q
0N
#555000
1Q
1N
#560000
0Q
0N
#565000
1Q
1N
#570000
0Q
0N
#575000
1P
1Q
1N
#580000
0Q
0N
#585000
0P
1Q
1N
#590000
0Q
0N
#595000
1Q
1N
#600000
0Q
0N
#605000
1Q
1B
0C
1N
#610000
0Q
0N
#615000
1Q
0B
1N
#620000
0Q
0N
#625000
1Q
1N
#630000
0Q
0N
#635000
1Q
1N
#640000
0Q
0N
#645000
1Q
1N
#650000
0Q
0N
#655000
1Q
1N
#660000
0Q
0N
#665000
1Q
1N
#670000
0Q
0N
#675000
1Q
1N
#680000
0Q
16
0N
#685000
1Q
1N
#690000
0Q
0N
#695000
1Q
1N
#700000
0Q
0N
#705000
1Q
1N
#710000
0Q
0N
#715000
1Q
1N
#720000
0Q
0N
#725000
1Q
1N
#730000
0Q
0N
#735000
1P
1Q
1N
#740000
0Q
0N
#745000
0P
1Q
1N
#750000
0Q
0N
#755000
1Q
1N
#760000
0Q
0N
#765000
1Q
1B
1C
1N
#770000
0Q
0N
#775000
1Q
0B
1F
1N
#780000
0Q
0N
#785000
1Q
1N
#790000
0Q
0N
#795000
1Q
1N
#800000
0Q
0N
#805000
1Q
1N
#810000
0Q
0N
#815000
1Q
1N
#820000
0Q
0N
#825000
1Q
1N
#830000
0Q
0N
#835000
1Q
1N
#840000
0Q
0N
#845000
1Q
1N
#850000
0Q
0N
#855000
1Q
1N
#860000
0Q
0N
#865000
1Q
1N
#870000
0Q
0N
#875000
1Q
1N
#880000
0Q
0N
#885000
1Q
1N
#890000
0Q
0N
#895000
1P
1Q
1N
#900000
0Q
0N
#905000
0P
1Q
1N
#910000
0Q
0N
#915000
1Q
1N
#920000
0Q
0N
#925000
1Q
1B
1N
#930000
0Q
0N
#935000
1Q
0B
1G
1N
#940000
0Q
0N
#945000
1Q
1N
#950000
0Q
0N
#955000
1Q
1N
#960000
0Q
0N
#965000
1Q
1N
#970000
0Q
0N
#975000
1Q
1N
#980000
0Q
0N
#985000
1Q
1N
#990000
0Q
0N
#995000
1Q
1N
#1000000
0Q
06
0N
#1005000
1Q
1N
#1010000
0Q
0N
#1015000
1Q
1N
#1020000
0Q
0N
#1025000
1Q
1N
#1030000
0Q
0N
#1035000
1Q
1N
#1040000
0Q
0N
#1045000
1Q
1N
#1050000
0Q
0N
#1055000
1P
1Q
1N
#1060000
0Q
0N
#1065000
0P
1Q
1N
#1070000
0Q
0N
#1075000
1Q
1N
#1080000
0Q
0N
#1085000
1Q
1B
0C
1N
#1090000
0Q
0N
#1095000
1Q
0B
1N
#1100000
0Q
0N
#1105000
1Q
1N
#1110000
0Q
0N
#1115000
1Q
1N
#1120000
0Q
0N
#1125000
1Q
1N
#1130000
0Q
0N
#1135000
1Q
1N
#1140000
0Q
0N
#1145000
1Q
1N
#1150000
0Q
0N
#1155000
1Q
1N
#1160000
0Q
0N
#1165000
1Q
1N
#1170000
0Q
0N
#1175000
1Q
1N
#1180000
0Q
0N
#1185000
1Q
1N
#1190000
0Q
0N
#1195000
1Q
1N
#1200000
0Q
0N
#1205000
1Q
1N
#1210000
0Q
0N
#1215000
1P
1Q
1N
#1220000
0Q
0N
#1225000
0P
1Q
1N
#1230000
0Q
0N
#1235000
1Q
1N
#1240000
0Q
0N
#1245000
1Q
1B
1N
#1250000
0Q
0N
#1255000
1Q
0B
1N
#1260000
0Q
0N
#1265000
1Q
1N
#1270000
0Q
0N
#1275000
1Q
1N
#1280000
0Q
0N
#1285000
1Q
1N
#1290000
0Q
0N
#1295000
1Q
1N
#1300000
0Q
0N
#1305000
1Q
1N
#1310000
0Q
0N
#1315000
1Q
1N
#1320000
0Q
16
0N
#1325000
1Q
1N
#1330000
0Q
0N
#1335000
1Q
1N
#1340000
0Q
0N
#1345000
1Q
1N
#1350000
0Q
0N
#1355000
1Q
1N
#1360000
0Q
0N
#1365000
1Q
1N
#1370000
0Q
0N
#1375000
1P
1Q
1N
#1380000
0Q
0N
#1385000
0P
1Q
1N
#1390000
0Q
0N
#1395000
1Q
1N
#1400000
0Q
0N
#1405000
1Q
1B
1C
1N
#1410000
0Q
0N
#1415000
1Q
0B
1J
1N
#1420000
0Q
0N
#1425000
1Q
1N
#1430000
0Q
0N
#1435000
1Q
1N
#1440000
0Q
0N
#1445000
1Q
1N
#1450000
0Q
0N
#1455000
1Q
1N
#1460000
0Q
0N
#1465000
1Q
1N
#1470000
0Q
0N
#1475000
1Q
1N
#1480000
0Q
06
0N
#1485000
1Q
1N
#1490000
0Q
0N
#1495000
1Q
1N
#1500000
0Q
0N
#1505000
1Q
1N
#1510000
0Q
0N
#1515000
1Q
1N
#1520000
0Q
0N
#1525000
1Q
1N
#1530000
0Q
0N
#1535000
1P
1Q
1N
#1540000
0Q
0N
#1545000
0P
1Q
1N
#1550000
0Q
0N
#1555000
1Q
1N
#1560000
0Q
0N
#1565000
1Q
1B
0C
1N
#1570000
0Q
0N
#1575000
1Q
0B
1N
#1580000
0Q
0N
#1585000
1Q
1N
#1590000
0Q
0N
#1595000
1Q
1N
#1600000
0Q
0N
#1605000
1Q
1N
#1610000
0Q
0N
#1615000
1Q
1N
#1620000
0Q
0N
#1625000
1Q
1N
#1630000
0Q
0N
#1635000
1Q
1N
#1640000
0Q
0N
#1645000
1Q
1N
#1650000
0Q
0N
#1655000
1Q
1N
#1660000
0Q
0N
#1665000
1Q
1N
#1670000
0Q
0N
#1675000
1Q
1N
#1680000
0Q
0N
#1685000
1Q
1N
#1690000
0Q
0N
#1695000
1P
1Q
1N
#1700000
0Q
0N
#1705000
0P
1Q
1N
#1710000
0Q
0N
#1715000
1Q
1N
#1720000
0Q
0N
#1725000
1Q
1B
1N
#1730000
0Q
0N
#1735000
1Q
0B
1N
#1740000
0Q
0N
#1745000
1Q
1N
#1750000
0Q
0N
#1755000
1Q
1N
#1760000
0Q
0N
#1765000
1Q
1N
#1770000
0Q
0N
#1775000
1Q
1N
#1780000
0Q
0N
#1785000
1Q
1N
#1790000
0Q
0N
#1795000
1Q
1N
#1800000
0Q
16
0N
#1805000
1Q
1N
#1810000
0Q
0N
#1815000
1Q
1N
#1820000
0Q
0N
#1825000
1Q
1N
#1830000
0Q
0N
#1835000
1Q
1N
#1840000
0Q
0N
#1845000
1Q
1N
#1850000
0Q
0N
#1855000
1P
1Q
1N
#1860000
0Q
0N
#1865000
0P
1Q
1N
#1870000
0Q
0N
#1875000
1Q
1N
#1880000
0Q
0N
#1885000
1Q
1B
1C
1N
#1890000
0Q
0N
#1895000
1Q
1>
0=
1<
1;
0:
09
18
07
1A
0B
1N
#1900000
0Q
0N
#1905000
1Q
1@
0A
1N
#1910000
0Q
0N
#1915000
1Q
0@
1N
#1920000
0Q
0N
#1925000
1Q
1N
#1930000
0Q
0N
#1935000
1Q
1N
#1940000
0Q
0N
#1945000
1Q
1N
#1950000
0Q
0N
#1955000
1Q
1N
#1960000
0Q
0N
#1965000
1Q
1N
#1970000
0Q
0N
#1975000
1Q
1N
#1980000
0Q
0N
#1985000
1Q
1N
#1990000
0Q
0N
#1995000
1Q
1N
#2000000
0Q
0N
#2005000
1Q
1N
#2010000
0Q
0N
#2015000
1P
1Q
1N
#2020000
0Q
0N
#2025000
0P
1Q
1N
#2030000
0Q
0N
#2035000
1Q
1N
#2040000
0Q
0N
#2045000
1Q
1N
#2050000
0Q
0N
#2055000
1Q
1N
#2060000
0Q
0N
#2065000
1Q
1N
#2070000
0Q
0N
#2075000
1Q
1N
#2080000
0Q
0N
#2085000
1Q
1N
#2090000
0Q
0N
#2095000
1Q
1N
#2100000
0Q
0N
#2105000
1Q
1N
#2110000
0Q
0N
#2115000
1Q
1N
#2120000
0Q
0N
#2125000
1Q
1N
#2130000
0Q
0N
#2135000
1Q
1N
#2140000
0Q
0N
#2145000
1Q
1N
#2150000
0Q
0N
#2155000
1Q
1N
#2160000
0Q
0N
#2165000
1Q
1N
#2170000
0Q
0N
#2175000
1P
1Q
1N
#2180000
0Q
0N
#2185000
0P
1Q
1N
#2190000
0Q
0N
#2195000
1Q
1N
#2200000
0Q
0N
#2205000
1Q
1N
#2210000
0Q
0N
#2215000
1Q
1N
#2220000
0Q
0N
#2225000
1Q
1N
#2230000
0Q
0N
#2235000
1Q
1N
#2240000
0Q
0N
#2245000
1Q
1N
#2250000
0Q
0N
#2255000
1Q
1N
#2260000
0Q
0N
#2265000
1Q
1N
#2270000
0Q
0N
#2275000
1Q
1N
#2280000
0Q
0N
#2285000
1Q
1N
#2290000
0Q
0N
#2295000
1Q
1N
#2300000
0Q
0N
#2305000
1Q
1N
#2310000
0Q
0N
#2315000
1Q
1N
#2320000
0Q
0N
#2325000
1Q
1N
#2330000
0Q
0N
#2335000
1P
1Q
1N
#2340000
0Q
0N
#2345000
0P
1Q
1N
#2350000
0Q
0N
#2355000
1Q
1N
#2360000
0Q
0N
#2365000
1Q
1N
#2370000
0Q
0N
#2375000
1Q
1N
#2380000
0Q
0N
#2385000
1Q
1N
#2390000
0Q
0N
#2395000
1Q
1N
#2400000
0Q
0N
#2405000
1Q
1N
#2410000
0Q
0N
#2415000
1Q
1N
#2420000
0Q
0N
#2425000
1Q
1N
#2430000
0Q
0N
#2435000
1Q
1N
#2440000
0Q
0N
#2445000
1Q
1N
#2450000
0Q
0N
#2455000
1Q
1N
#2460000
0Q
0N
#2465000
1Q
1N
#2470000
0Q
0N
#2475000
1Q
1N
#2480000
0Q
0N
#2485000
1Q
1N
#2490000
0Q
0N
#2495000
1P
1Q
1N
#2500000
0Q
0N
#2505000
0P
1Q
1N
#2510000
0Q
0N
#2515000
1Q
1N
#2520000
0Q
0N
#2525000
1Q
1N
#2530000
0Q
0N
#2535000
1Q
1N
#2540000
0Q
0N
#2545000
1Q
1N
#2550000
0Q
0N
#2555000
1Q
1N
#2560000
0Q
0N
#2565000
1Q
1N
#2570000
0Q
0N
#2575000
1Q
1N
#2580000
0Q
0N
#2585000
1Q
1N
#2590000
0Q
0N
#2595000
1Q
1N
#2600000
0Q
0N
#2605000
1Q
1N
#2610000
0Q
0N
#2615000
1Q
1N
#2620000
0Q
0N
#2625000
1Q
1N
#2630000
0Q
0N
#2635000
1Q
1N
#2640000
0Q
0N
#2645000
1Q
1N
#2650000
0Q
0N
#2655000
1P
1Q
1N
#2660000
0Q
0N
#2665000
0P
1Q
1N
#2670000
0Q
0N
#2675000
1Q
1N
#2680000
0Q
0N
#2685000
1Q
1N
#2690000
0Q
0N
#2695000
1Q
1N
#2700000
0Q
0N
#2705000
1Q
1N
#2710000
0Q
0N
#2715000
1Q
1N
#2720000
0Q
0N
#2725000
1Q
1N
#2730000
0Q
0N
#2735000
1Q
1N
#2740000
0Q
0N
#2745000
1Q
1N
#2750000
0Q
0N
#2755000
1Q
1N
#2760000
0Q
0N
#2765000
1Q
1N
#2770000
0Q
0N
#2775000
1Q
1N
#2780000
0Q
0N
#2785000
1Q
1N
#2790000
0Q
0N
#2795000
1Q
1N
#2800000
0Q
0N
#2805000
1Q
1N
#2810000
0Q
0N
#2815000
1P
1Q
1N
#2820000
0Q
0N
#2825000
0P
1Q
1N
#2830000
0Q
0N
#2835000
1Q
1N
#2840000
0Q
0N
#2845000
1Q
1N
#2850000
0Q
0N
#2855000
1Q
1N
#2860000
0Q
0N
#2865000
1Q
1N
#2870000
0Q
0N
#2875000
1Q
1N
#2880000
0Q
0N
#2885000
1Q
1N
#2890000
0Q
0N
#2895000
1Q
1N
#2900000
0Q
0N
#2905000
1Q
1N
#2910000
0Q
0N
#2915000
1Q
1N
#2920000
0Q
0N
#2925000
1Q
1N
#2930000
0Q
0N
#2935000
1Q
1N
#2940000
0Q
0N
#2945000
1Q
1N
#2950000
0Q
0N
#2955000
1Q
1N
#2960000
0Q
0N
#2965000
1Q
1N
#2970000
0Q
0N
#2975000
1P
1Q
1N
#2980000
0Q
0N
#2985000
0P
1Q
1N
#2990000
0Q
0N
#2995000
1Q
1N
#3000000
0Q
0N
#3005000
1Q
1N
#3010000
0Q
0N
#3015000
1Q
1N
#3020000
0Q
0N
#3025000
1Q
1N
#3030000
0Q
0N
#3035000
1Q
1N
#3040000
0Q
0N
#3045000
1Q
1N
#3050000
0Q
0N
#3055000
1Q
1N
#3060000
0Q
0N
#3065000
1Q
1N
#3070000
0Q
0N
#3075000
1Q
1N
#3080000
0Q
0N
#3085000
1Q
1N
#3090000
0Q
0N
#3095000
1Q
1N
#3100000
0Q
0N
#3105000
1Q
1N
#3110000
0Q
0N
#3115000
1Q
1N
#3120000
0Q
0N
#3125000
1Q
1N
#3130000
0Q
0N
#3135000
1P
1Q
1N
#3140000
0Q
0N
#3145000
0P
1Q
1N
#3150000
0Q
0N
#3155000
1Q
1N
#3160000
0Q
0N
#3165000
1Q
1N
#3170000
0Q
0N
#3175000
1Q
1N
#3180000
0Q
0N
#3185000
1Q
1N
#3190000
0Q
0N
#3195000
1Q
1N
#3200000
0Q
0N
#3205000
1Q
1N
#3210000
0Q
0N
#3215000
1Q
1N
#3220000
0Q
0N
#3225000
1Q
1N
#3230000
0Q
0N
#3235000
1Q
1N
#3240000
0Q
0N
#3245000
1Q
1N
#3250000
0Q
0N
#3255000
1Q
1N
#3260000
0Q
0N
#3265000
1Q
1N
#3270000
0Q
0N
#3275000
1Q
1N
#3280000
0Q
0N
#3285000
1Q
1N
#3290000
0Q
0N
#3295000
1P
1Q
1N
#3300000
0Q
0N
#3305000
0P
1Q
1N
#3310000
0Q
0N
#3315000
1Q
1N
#3320000
0Q
0N
#3325000
1Q
1N
#3330000
0Q
0N
#3335000
1Q
1N
#3340000
0Q
0N
#3345000
1Q
1N
#3350000
0Q
0N
#3355000
1Q
1N
#3360000
0Q
0N
#3365000
1Q
1N
#3370000
0Q
0N
#3375000
1Q
1N
#3380000
0Q
0N
#3385000
1Q
1N
#3390000
0Q
0N
#3395000
1Q
1N
#3400000
0Q
0N
#3405000
1Q
1N
#3410000
0Q
0N
#3415000
1Q
1N
#3420000
0Q
0N
#3425000
1Q
1N
#3430000
0Q
0N
#3435000
1Q
1N
#3440000
0Q
0N
#3445000
1Q
1N
#3450000
0Q
0N
#3455000
1P
1Q
1N
#3460000
0Q
0N
#3465000
0P
1Q
1N
#3470000
0Q
0N
#3475000
1Q
1N
#3480000
0Q
0N
#3485000
1Q
1N
#3490000
0Q
0N
#3495000
1Q
1N
#3500000
0Q
0N
#3505000
1Q
1N
#3510000
0Q
0N
#3515000
1Q
1N
#3520000
0Q
0N
#3525000
1Q
1N
#3530000
0Q
0N
#3535000
1Q
1N
#3540000
0Q
0N
#3545000
1Q
1N
#3550000
0Q
0N
#3555000
1Q
1N
#3560000
0Q
0N
#3565000
1Q
1N
#3570000
0Q
0N
#3575000
1Q
1N
#3580000
0Q
0N
#3585000
1Q
1N
#3590000
0Q
0N
#3595000
1Q
1N
#3600000
0Q
0N
#3605000
1Q
1N
#3610000
0Q
0N
#3615000
1P
1Q
1N
#3620000
0Q
0N
#3625000
0P
1Q
1N
#3630000
0Q
0N
#3635000
1Q
1N
#3640000
0Q
0N
#3645000
1Q
1N
#3650000
0Q
0N
#3655000
1Q
1N
#3660000
0Q
0N
#3665000
1Q
1N
#3670000
0Q
0N
#3675000
1Q
1N
#3680000
0Q
0N
#3685000
1Q
1N
#3690000
0Q
0N
#3695000
1Q
1N
#3700000
0Q
0N
#3705000
1Q
1N
#3710000
0Q
0N
#3715000
1Q
1N
#3720000
0Q
0N
#3725000
1Q
1N
#3730000
0Q
0N
#3735000
1Q
1N
#3740000
0Q
0N
#3745000
1Q
1N
#3750000
0Q
0N
#3755000
1Q
1N
#3760000
0Q
0N
#3765000
1Q
1N
#3770000
0Q
0N
#3775000
1P
1Q
1N
#3780000
0Q
0N
#3785000
0P
1Q
1N
#3790000
0Q
0N
#3795000
1Q
1N
#3800000
0Q
0N
#3805000
1Q
1N
#3810000
0Q
0N
#3815000
1Q
1N
#3820000
0Q
0N
#3825000
1Q
1N
#3830000
0Q
0N
#3835000
1Q
1N
#3840000
0Q
0N
#3845000
1Q
1N
#3850000
0Q
0N
#3855000
1Q
1N
#3860000
0Q
0N
#3865000
1Q
1N
#3870000
0Q
0N
#3875000
1Q
1N
#3880000
0Q
0N
#3885000
1Q
1N
#3890000
0Q
0N
#3895000
1Q
1N
#3900000
0Q
0N
#3905000
1Q
1N
#3910000
0Q
0N
#3915000
1Q
1N
#3920000
0Q
0N
#3925000
1Q
1N
#3930000
0Q
0N
#3935000
1P
1Q
1N
#3940000
0Q
0N
#3945000
0P
1Q
1N
#3950000
0Q
0N
#3955000
1Q
1N
#3960000
0Q
0N
#3965000
1Q
1N
#3970000
0Q
0N
#3975000
1Q
1N
#3980000
0Q
0N
#3985000
1Q
1N
#3990000
0Q
0N
#3995000
1Q
1N
#4000000
0Q
0N
#4005000
1Q
1N
#4010000
0Q
0N
#4015000
1Q
1N
#4020000
0Q
0N
#4025000
1Q
1N
#4030000
0Q
0N
#4035000
1Q
1N
#4040000
0Q
0N
#4045000
1Q
1N
#4050000
0Q
0N
#4055000
1Q
1N
#4060000
0Q
0N
#4065000
1Q
1N
#4070000
0Q
0N
#4075000
1Q
1N
#4080000
0Q
0N
#4085000
1Q
1N
#4090000
0Q
0N
#4095000
1P
1Q
1N
#4100000
0Q
0N
#4105000
0P
1Q
1N
#4110000
0Q
0N
#4115000
1Q
1N
#4120000
0Q
0N
#4125000
1Q
1N
#4130000
0Q
0N
#4135000
1Q
1N
